build/lib/pydantic_configmanager/__init__.py
build/lib/pydantic_configmanager/main.py
pydantic_configmanager/__init__.py
pydantic_configmanager/main.py
pydantic_configmanager-0.1.1.dist-info/LICENSE
pydantic_configmanager-0.1.1.dist-info/METADATA
pydantic_configmanager-0.1.1.dist-info/WHEEL
pydantic_configmanager-0.1.1.dist-info/top_level.txt
pydantic_configmanager-0.1.1.dist-info/RECORD
