Metadata-Version: 2.1
Name: pydantic-configmanager
Version: 0.1.1
Summary: Get configurations with the help of pydantic
Home-page: UNKNOWN
Author: Filipe Spencer Lopes
Author-email: filipe@spncr.be
License: UNKNOWN
Platform: UNKNOWN
Classifier: Development Status :: 3 - Alpha
Classifier: Intended Audience :: Developers
Classifier: Topic :: Software Development :: Build Tools
Classifier: License :: OSI Approved :: MIT License
Classifier: Programming Language :: Python :: 3.6
Classifier: Programming Language :: Python :: 3.7
Classifier: Programming Language :: Python :: 3.8
Requires-Python: >=3.6.8, <4
Requires-Dist: pydantic
Provides-Extra: dev
Requires-Dist: check-manifest ; extra == 'dev'
Provides-Extra: test
Requires-Dist: coverage ; extra == 'test'
